[    {        "CreditCard": {            "IssuingNetwork": "Discover",            "CardNumber": "6011050879504115",            "Name": "Alivia Mitchell",            "Address": "Arlington Avenue 65",            "Country": "Hungary",            "CVV": "881",            "Exp": "04/2021"        }    },    {        "CreditCard": {            "IssuingNetwork": "Discover",            "CardNumber": "6011479428051437",            "Name": "Gideon Green",            "Address": "Olive Street 25",            "Country": "Malaysia",            "CVV": "966",            "Exp": "06/2020"        }    },    {        "CreditCard": {            "IssuingNetwork": "Discover",            "CardNumber": "6011664364492105",            "Name": "Noah Jackson",            "Address": "Charles Street 3",            "Country": "Morocco",            "CVV": "876",            "Exp": "03/2026"        }    },    {        "CreditCard": {            "IssuingNetwork": "Discover",            "CardNumber": "6011376183961976",            "Name": "Elijah Evans",            "Address": "Devon Court 36",            "Country": "Fiji",            "CVV": "573",            "Exp": "02/2020"        }    },    {        "CreditCard": {            "IssuingNetwork": "Discover",            "CardNumber": "6011493170331186",            "Name": "Sydnee Perez",            "Address": "Devon Court 55",            "Country": "Cyprus",            "CVV": "230",            "Exp": "10/2024"        }    },    {        "CreditCard": {            "IssuingNetwork": "Discover",            "CardNumber": "6011346589611236",            "Name": "Clay Campbell",            "Address": "Cedar Lane 22",            "Country": "Reunion",            "CVV": "771",            "Exp": "12/2018"        }    },    {        "CreditCard": {            "IssuingNetwork": "Discover",            "CardNumber": "6011964045590891",            "Name": "Wendy Martin",            "Address": "Jefferson Avenue 125",            "Country": "Sweden",            "CVV": "383",            "Exp": "03/2023"        }    },    {        "CreditCard": {            "IssuingNetwork": "Discover",            "CardNumber": "6011165351905521",            "Name": "Ishaan Perez",            "Address": "Highland Drive 21",            "Country": "Nigeria",            "CVV": "747",            "Exp": "03/2021"        }    },    {        "CreditCard": {            "IssuingNetwork": "Discover",            "CardNumber": "6011810529732154",            "Name": "Brianna White",            "Address": "Clay Street 142",            "Country": "Monaco",            "CVV": "889",            "Exp": "04/2027"        }    },    {        "CreditCard": {            "IssuingNetwork": "Discover",            "CardNumber": "6011402951655143",            "Name": "Abraham Gonzalez",            "Address": "Pleasant Street 68",            "Country": "Netherlands",            "CVV": "884",            "Exp": "09/2027"        }    },    {        "CreditCard": {            "IssuingNetwork": "Discover",            "CardNumber": "6011126462653145",            "Name": "Jazlynn Garcia",            "Address": "River Street 56",            "Country": "Malaysia",            "CVV": "661",            "Exp": "05/2025"        }    },    {        "CreditCard": {            "IssuingNetwork": "Discover",            "CardNumber": "6011174936765962",            "Name": "Brenton Carter",            "Address": "Briarwood Drive 92",            "Country": "Vanuatu",            "CVV": "402",            "Exp": "03/2023"        }    },    {        "CreditCard": {            "IssuingNetwork": "Discover",            "CardNumber": "6011326993745598",            "Name": "Aydan Clark",            "Address": "Route 30 36",            "Country": "Andorra",            "CVV": "123",            "Exp": "07/2025"        }    },    {        "CreditCard": {            "IssuingNetwork": "Discover",            "CardNumber": "6011154363313957",            "Name": "Ruby Lee",            "Address": "Clay Street 126",            "Country": "South Africa",            "CVV": "879",            "Exp": "12/2018"        }    },    {        "CreditCard": {            "IssuingNetwork": "Discover",            "CardNumber": "6011944897632652",            "Name": "Diamond Robinson",            "Address": "Ann Street 14",            "Country": "United States",            "CVV": "571",            "Exp": "09/2027"        }    },    {        "CreditCard": {            "IssuingNetwork": "Discover",            "CardNumber": "6011920734843520",            "Name": "Camilla Brown",            "Address": "Linden Avenue 98",            "Country": "Greenland",            "CVV": "439",            "Exp": "01/2022"        }    },    {        "CreditCard": {            "IssuingNetwork": "Discover",            "CardNumber": "6011173610905159",            "Name": "Atticus Lee",            "Address": "Heather Lane 136",            "Country": "Armenia",            "CVV": "976",            "Exp": "09/2023"        }    },    {        "CreditCard": {            "IssuingNetwork": "Discover",            "CardNumber": "6011171390629007",            "Name": "Anthony Mitchell",            "Address": "Madison Avenue 6",            "Country": "Ecuador",            "CVV": "955",            "Exp": "04/2026"        }    },    {        "CreditCard": {            "IssuingNetwork": "Discover",            "CardNumber": "6011513093497317",            "Name": "Gideon Thomas",            "Address": "Rose Street 64",            "Country": "Rwanda",            "CVV": "777",            "Exp": "08/2025"        }    },    {        "CreditCard": {            "IssuingNetwork": "Discover",            "CardNumber": "6011036497916567",            "Name": "Ashley Anderson",            "Address": "Rose Street 35",            "Country": "Western Sahara",            "CVV": "677",            "Exp": "03/2020"        }    },    {        "CreditCard": {            "IssuingNetwork": "Discover",            "CardNumber": "6011179808949537",            "Name": "Miranda Johnson",            "Address": "Briarwood Drive 71",            "Country": "Sweden",            "CVV": "392",            "Exp": "03/2019"        }    },    {        "CreditCard": {            "IssuingNetwork": "Discover",            "CardNumber": "6011488595881914",            "Name": "Joy Brown",            "Address": "Windsor Drive 143",            "Country": "Sweden",            "CVV": "448",            "Exp": "10/2024"        }    },    {        "CreditCard": {            "IssuingNetwork": "Discover",            "CardNumber": "6011497811611104",            "Name": "Gideon Hernandez",            "Address": "Hanover Court 26",            "Country": "Japan",            "CVV": "576",            "Exp": "12/2021"        }    },    {        "CreditCard": {            "IssuingNetwork": "Discover",            "CardNumber": "6011186755680965",            "Name": "Reagan Johnson",            "Address": "Devon Court 125",            "Country": "Comoros",            "CVV": "664",            "Exp": "12/2022"        }    },    {        "CreditCard": {            "IssuingNetwork": "Discover",            "CardNumber": "6011177711925065",            "Name": "Ashley Young",            "Address": "Route 1 66",            "Country": "Sierra Leone",            "CVV": "463",            "Exp": "12/2018"        }    },    {        "CreditCard": {            "IssuingNetwork": "Discover",            "CardNumber": "6011343221501602",            "Name": "Elizabeth Hill",            "Address": "Heather Lane 138",            "Country": "Tonga",            "CVV": "120",            "Exp": "12/2018"        }    },    {        "CreditCard": {            "IssuingNetwork": "Discover",            "CardNumber": "6011802365422552",            "Name": "Avery Moore",            "Address": "Briarwood Drive 11",            "Country": "Aruba",            "CVV": "691",            "Exp": "07/2024"        }    },    {        "CreditCard": {            "IssuingNetwork": "Discover",            "CardNumber": "6011656881840907",            "Name": "Malcolm Garcia",            "Address": "Franklin Court 146",            "Country": "France",            "CVV": "477",            "Exp": "08/2027"        }    },    {        "CreditCard": {            "IssuingNetwork": "Discover",            "CardNumber": "6011605399287689",            "Name": "Dulce Lewis",            "Address": "Ann Street 97",            "Country": "Singapore",            "CVV": "438",            "Exp": "11/2025"        }    },    {        "CreditCard": {            "IssuingNetwork": "Discover",            "CardNumber": "6011316266139330",            "Name": "Aydan Robinson",            "Address": "Andover Court 137",            "Country": "Saint Lucia",            "CVV": "921",            "Exp": "04/2023"        }    },    {        "CreditCard": {            "IssuingNetwork": "Discover",            "CardNumber": "6011159167816717",            "Name": "Elvis Baker",            "Address": "Laurel Drive 44",            "Country": "Australia",            "CVV": "884",            "Exp": "07/2027"        }    },    {        "CreditCard": {            "IssuingNetwork": "Discover",            "CardNumber": "6011571878012420",            "Name": "Saige Johnson",            "Address": "Olive Street 71",            "Country": "Germany",            "CVV": "766",            "Exp": "03/2027"        }    },    {        "CreditCard": {            "IssuingNetwork": "Discover",            "CardNumber": "6011720139801747",            "Name": "Humberto Jones",            "Address": "Essex Court 110",            "Country": "St. Helena",            "CVV": "445",            "Exp": "05/2025"        }    },    {        "CreditCard": {            "IssuingNetwork": "Discover",            "CardNumber": "6011870190651943",            "Name": "Emma Walker",            "Address": "Essex Court 49",            "Country": "United Kingdom",            "CVV": "473",            "Exp": "09/2020"        }    },    {        "CreditCard": {            "IssuingNetwork": "Discover",            "CardNumber": "6011242404352793",            "Name": "Ethen Martinez",            "Address": "Hanover Court 47",            "Country": "Iceland",            "CVV": "810",            "Exp": "10/2023"        }    },    {        "CreditCard": {            "IssuingNetwork": "Discover",            "CardNumber": "6011807737977803",            "Name": "Addison Lewis",            "Address": "Highland Drive 57",            "Country": "Togo",            "CVV": "120",            "Exp": "12/2018"        }    },    {        "CreditCard": {            "IssuingNetwork": "Discover",            "CardNumber": "6011844379041952",            "Name": "Ethen Smith",            "Address": "River Street 43",            "Country": "Lesotho",            "CVV": "536",            "Exp": "02/2019"        }    },    {        "CreditCard": {            "IssuingNetwork": "Discover",            "CardNumber": "6011409883994383",            "Name": "Holly Thompson",            "Address": "Fairway Drive 135",            "Country": "Palau",            "CVV": "992",            "Exp": "09/2026"        }    },    {        "CreditCard": {            "IssuingNetwork": "Discover",            "CardNumber": "6011578953351110",            "Name": "Brooklyn Phillips",            "Address": "Garfield Avenue 144",            "Country": "Cuba",            "CVV": "133",            "Exp": "03/2020"        }    },    {        "CreditCard": {            "IssuingNetwork": "Discover",            "CardNumber": "6011269489135777",            "Name": "Aiden Allen",            "Address": "Summit Avenue 119",            "Country": "Sweden",            "CVV": "969",            "Exp": "10/2024"        }    },    {        "CreditCard": {            "IssuingNetwork": "Discover",            "CardNumber": "6011955384781737",            "Name": "Jeramiah Garcia",            "Address": "Country Club Road 125",            "Country": "Solomon Islands",            "CVV": "945",            "Exp": "03/2026"        }    },    {        "CreditCard": {            "IssuingNetwork": "Discover",            "CardNumber": "6011548342274620",            "Name": "Madison Edwards",            "Address": "Monroe Street 52",            "Country": "Estonia",            "CVV": "650",            "Exp": "09/2019"        }    },    {        "CreditCard": {            "IssuingNetwork": "Discover",            "CardNumber": "6011041667169047",            "Name": "Ryleigh Baker",            "Address": "Country Club Road 117",            "Country": "Colombia",            "CVV": "589",            "Exp": "08/2023"        }    },    {        "CreditCard": {            "IssuingNetwork": "Discover",            "CardNumber": "6011633333064618",            "Name": "Gavin Collins",            "Address": "Fairway Drive 145",            "Country": "Tuvalu",            "CVV": "998",            "Exp": "01/2022"        }    },    {        "CreditCard": {            "IssuingNetwork": "Discover",            "CardNumber": "6011666975986938",            "Name": "Xzavier Evans",            "Address": "Highland Drive 93",            "Country": "Mexico",            "CVV": "449",            "Exp": "12/2018"        }    },    {        "CreditCard": {            "IssuingNetwork": "Discover",            "CardNumber": "6011812150470252",            "Name": "Alyssa Taylor",            "Address": "Highland Drive 132",            "Country": "Uruguay",            "CVV": "294",            "Exp": "12/2018"        }    },    {        "CreditCard": {            "IssuingNetwork": "Discover",            "CardNumber": "6011558132471047",            "Name": "Dexter Turner",            "Address": "Jefferson Avenue 149",            "Country": "Kuwait",            "CVV": "887",            "Exp": "05/2026"        }    },    {        "CreditCard": {            "IssuingNetwork": "Discover",            "CardNumber": "6011536042940954",            "Name": "Amani Phillips",            "Address": "Forest Street 141",            "Country": "Sweden",            "CVV": "768",            "Exp": "12/2021"        }    },    {        "CreditCard": {            "IssuingNetwork": "Discover",            "CardNumber": "6011245339231115",            "Name": "Rihanna Lewis",            "Address": "Windsor Drive 3",            "Country": "Armenia",            "CVV": "268",            "Exp": "09/2026"        }    },    {        "CreditCard": {            "IssuingNetwork": "Discover",            "CardNumber": "6011978222961444",            "Name": "Saige Nelson",            "Address": "Charles Street 17",            "Country": "Kenya",            "CVV": "125",            "Exp": "10/2027"        }    },    {        "CreditCard": {            "IssuingNetwork": "Discover",            "CardNumber": "6011510758897161",            "Name": "Joseph Collins",            "Address": "Atlantic Avenue 25",            "Country": "Hungary",            "CVV": "372",            "Exp": "10/2026"        }    },    {        "CreditCard": {            "IssuingNetwork": "Discover",            "CardNumber": "6011639889090535",            "Name": "Christopher Jones",            "Address": "Windsor Drive 42",            "Country": "United Kingdom",            "CVV": "820",            "Exp": "05/2025"        }    },    {        "CreditCard": {            "IssuingNetwork": "Discover",            "CardNumber": "6011685383698562",            "Name": "Michael Anderson",            "Address": "Main Street 46",            "Country": "San Marino",            "CVV": "223",            "Exp": "02/2025"        }    },    {        "CreditCard": {            "IssuingNetwork": "Discover",            "CardNumber": "6011977938368183",            "Name": "Brooklyn Martinez",            "Address": "Clay Street 101",            "Country": "Uzbekistan",            "CVV": "556",            "Exp": "08/2026"        }    },    {        "CreditCard": {            "IssuingNetwork": "Discover",            "CardNumber": "6011747671865582",            "Name": "Emmanuel Brown",            "Address": "Willow Avenue 138",            "Country": "Italy",            "CVV": "813",            "Exp": "02/2021"        }    },    {        "CreditCard": {            "IssuingNetwork": "Discover",            "CardNumber": "6011551136576531",            "Name": "Amya Roberts",            "Address": "Cottage Street 48",            "Country": "Uruguay",            "CVV": "484",            "Exp": "03/2020"        }    },    {        "CreditCard": {            "IssuingNetwork": "Discover",            "CardNumber": "6011474998678883",            "Name": "Isabelle Parker",            "Address": "Devon Court 97",            "Country": "Netherlands",            "CVV": "397",            "Exp": "05/2027"        }    },    {        "CreditCard": {            "IssuingNetwork": "Discover",            "CardNumber": "6011449376443530",            "Name": "Kathy White",            "Address": "Front Street North 104",            "Country": "Liberia",            "CVV": "159",            "Exp": "01/2026"        }    },    {        "CreditCard": {            "IssuingNetwork": "Discover",            "CardNumber": "6011012587291310",            "Name": "Brooklyn Adams",            "Address": "Franklin Avenue 68",            "Country": "Egypt",            "CVV": "854",            "Exp": "02/2019"        }    },    {        "CreditCard": {            "IssuingNetwork": "Discover",            "CardNumber": "6011755619634168",            "Name": "Bryan Scott",            "Address": "Clay Street 94",            "Country": "Aruba",            "CVV": "703",            "Exp": "04/2021"        }    },    {        "CreditCard": {            "IssuingNetwork": "Discover",            "CardNumber": "6011497132153471",            "Name": "Cesar Brown",            "Address": "Charles Street 74",            "Country": "Turkmenistan",            "CVV": "688",            "Exp": "04/2027"        }    },    {        "CreditCard": {            "IssuingNetwork": "Discover",            "CardNumber": "6011847177697867",            "Name": "Alyssa Jones",            "Address": "Devon Court 129",            "Country": "Iceland",            "CVV": "506",            "Exp": "12/2018"        }    },    {        "CreditCard": {            "IssuingNetwork": "Discover",            "CardNumber": "6011173731524772",            "Name": "Tristan Brown",            "Address": "Linden Avenue 111",            "Country": "Philippines",            "CVV": "575",            "Exp": "12/2018"        }    },    {        "CreditCard": {            "IssuingNetwork": "Discover",            "CardNumber": "6011428754576467",            "Name": "Jolie Evans",            "Address": "Crescent Street 60",            "Country": "Tokelau",            "CVV": "336",            "Exp": "06/2024"        }    },    {        "CreditCard": {            "IssuingNetwork": "Discover",            "CardNumber": "6011481639237664",            "Name": "Van Edwards",            "Address": "Olive Street 90",            "Country": "Angola",            "CVV": "233",            "Exp": "12/2018"        }    },    {        "CreditCard": {            "IssuingNetwork": "Discover",            "CardNumber": "6011385548746352",            "Name": "Samantha King",            "Address": "Cedar Lane 138",            "Country": "Uruguay",            "CVV": "713",            "Exp": "07/2024"        }    },    {        "CreditCard": {            "IssuingNetwork": "Discover",            "CardNumber": "6011789718706486",            "Name": "Miranda Scott",            "Address": "Willow Avenue 93",            "Country": "Senegal",            "CVV": "406",            "Exp": "02/2022"        }    },    {        "CreditCard": {            "IssuingNetwork": "Discover",            "CardNumber": "6011330970313065",            "Name": "Dallas Miller",            "Address": "Olive Street 3",            "Country": "Australia",            "CVV": "901",            "Exp": "08/2019"        }    },    {        "CreditCard": {            "IssuingNetwork": "Discover",            "CardNumber": "6011778471239645",            "Name": "Reuben Anderson",            "Address": "King Street 84",            "Country": "France",            "CVV": "646",            "Exp": "01/2026"        }    },    {        "CreditCard": {            "IssuingNetwork": "Discover",            "CardNumber": "6011576497319973",            "Name": "Emmy Jones",            "Address": "Country Club Road 81",            "Country": "Cameroon",            "CVV": "455",            "Exp": "06/2024"        }    },    {        "CreditCard": {            "IssuingNetwork": "Discover",            "CardNumber": "6011554543907778",            "Name": "Isabella Lewis",            "Address": "Franklin Court 80",            "Country": "Tunisia",            "CVV": "653",            "Exp": "04/2022"        }    },    {        "CreditCard": {            "IssuingNetwork": "Discover",            "CardNumber": "6011286888066155",            "Name": "Etha Brown",            "Address": "Warren Avenue 27",            "Country": "Singapore",            "CVV": "167",            "Exp": "07/2019"        }    },    {        "CreditCard": {            "IssuingNetwork": "Discover",            "CardNumber": "6011613845153539",            "Name": "Dallas Mitchell",            "Address": "Cedar Avenue 150",            "Country": "Singapore",            "CVV": "177",            "Exp": "01/2027"        }    },    {        "CreditCard": {            "IssuingNetwork": "Discover",            "CardNumber": "6011243132635178",            "Name": "Paris Wilson",            "Address": "Laurel Lane 25",            "Country": "Greece",            "CVV": "843",            "Exp": "06/2026"        }    },    {        "CreditCard": {            "IssuingNetwork": "Discover",            "CardNumber": "6011103377124900",            "Name": "Amber Miller",            "Address": "Windsor Drive 88",            "Country": "Italy",            "CVV": "771",            "Exp": "07/2027"        }    },    {        "CreditCard": {            "IssuingNetwork": "Discover",            "CardNumber": "6011858505802152",            "Name": "Aydan Nelson",            "Address": "Cedar Avenue 15",            "Country": "Lesotho",            "CVV": "474",            "Exp": "04/2022"        }    },    {        "CreditCard": {            "IssuingNetwork": "Discover",            "CardNumber": "6011178282437613",            "Name": "Riley Anderson",            "Address": "Olive Street 50",            "Country": "Qatar",            "CVV": "280",            "Exp": "08/2020"        }    },    {        "CreditCard": {            "IssuingNetwork": "Discover",            "CardNumber": "6011253266387843",            "Name": "Aldo Anderson",            "Address": "Cedar Avenue 68",            "Country": "Colombia",            "CVV": "826",            "Exp": "04/2024"        }    },    {        "CreditCard": {            "IssuingNetwork": "Discover",            "CardNumber": "6011537972743178",            "Name": "David Perez",            "Address": "Grand Avenue 46",            "Country": "Marshall Islands",            "CVV": "498",            "Exp": "01/2019"        }    },    {        "CreditCard": {            "IssuingNetwork": "Discover",            "CardNumber": "6011969933921736",            "Name": "Natalie Scott",            "Address": "Andover Court 15",            "Country": "Singapore",            "CVV": "392",            "Exp": "05/2019"        }    },    {        "CreditCard": {            "IssuingNetwork": "Discover",            "CardNumber": "6011568165573825",            "Name": "Brooklyn Harris",            "Address": "Briarwood Drive 45",            "Country": "Sweden",            "CVV": "153",            "Exp": "10/2023"        }    },    {        "CreditCard": {            "IssuingNetwork": "Discover",            "CardNumber": "6011026053543657",            "Name": "Ashley Turner",            "Address": "Franklin Court 123",            "Country": "New Caledonia",            "CVV": "438",            "Exp": "05/2025"        }    },    {        "CreditCard": {            "IssuingNetwork": "Discover",            "CardNumber": "6011775461624414",            "Name": "Samantha Miller",            "Address": "Hanover Court 75",            "Country": "Netherlands",            "CVV": "289",            "Exp": "03/2026"        }    },    {        "CreditCard": {            "IssuingNetwork": "Discover",            "CardNumber": "6011484319560629",            "Name": "Madison Moore",            "Address": "Madison Avenue 94",            "Country": "Portugal",            "CVV": "569",            "Exp": "09/2025"        }    },    {        "CreditCard": {            "IssuingNetwork": "Discover",            "CardNumber": "6011380435584057",            "Name": "Etha Williams",            "Address": "Cedar Avenue 53",            "Country": "New Zealand",            "CVV": "933",            "Exp": "10/2020"        }    },    {        "CreditCard": {            "IssuingNetwork": "Discover",            "CardNumber": "6011858975445136",            "Name": "Tyrese Taylor",            "Address": "Franklin Avenue 141",            "Country": "Zambia",            "CVV": "814",            "Exp": "12/2018"        }    },    {        "CreditCard": {            "IssuingNetwork": "Discover",            "CardNumber": "6011943409405730",            "Name": "Jolie Lewis",            "Address": "Monroe Street 100",            "Country": "Mayotte",            "CVV": "404",            "Exp": "04/2025"        }    },    {        "CreditCard": {            "IssuingNetwork": "Discover",            "CardNumber": "6011989449769775",            "Name": "Marisol Lopez",            "Address": "Garfield Avenue 4",            "Country": "Chile",            "CVV": "840",            "Exp": "03/2027"        }    },    {        "CreditCard": {            "IssuingNetwork": "Discover",            "CardNumber": "6011439236635284",            "Name": "Gabriel Mitchell",            "Address": "Cedar Avenue 148",            "Country": "Nigeria",            "CVV": "327",            "Exp": "06/2027"        }    },    {        "CreditCard": {            "IssuingNetwork": "Discover",            "CardNumber": "6011329415386231",            "Name": "Cierra Adams",            "Address": "Andover Court 37",            "Country": "Italy",            "CVV": "985",            "Exp": "12/2018"        }    },    {        "CreditCard": {            "IssuingNetwork": "Discover",            "CardNumber": "6011197336636236",            "Name": "Landon Jackson",            "Address": "Olive Street 122",            "Country": "Afghanistan",            "CVV": "760",            "Exp": "07/2021"        }    },    {        "CreditCard": {            "IssuingNetwork": "Discover",            "CardNumber": "6011642449666141",            "Name": "Michael Jones",            "Address": "Charles Street 63",            "Country": "Singapore",            "CVV": "976",            "Exp": "12/2018"        }    },    {        "CreditCard": {            "IssuingNetwork": "Discover",            "CardNumber": "6011705960870846",            "Name": "Hannah Baker",            "Address": "Court Street 81",            "Country": "Bahrain",            "CVV": "504",            "Exp": "11/2023"        }    },    {        "CreditCard": {            "IssuingNetwork": "Discover",            "CardNumber": "6011821018507445",            "Name": "Miah Clark",            "Address": "Forest Street 75",            "Country": "Swaziland",            "CVV": "191",            "Exp": "02/2022"        }    },    {        "CreditCard": {            "IssuingNetwork": "Discover",            "CardNumber": "6011292523035050",            "Name": "Emmy Allen",            "Address": "Jefferson Avenue 113",            "Country": "Ukraine",            "CVV": "436",            "Exp": "01/2027"        }    },    {        "CreditCard": {            "IssuingNetwork": "Discover",            "CardNumber": "6011116553671213",            "Name": "Walker Campbell",            "Address": "Cedar Lane 140",            "Country": "Ethiopia",            "CVV": "322",            "Exp": "04/2019"        }    },    {        "CreditCard": {            "IssuingNetwork": "Discover",            "CardNumber": "6011803993440545",            "Name": "Tristan Turner",            "Address": "Woodland Drive 115",            "Country": "Hungary",            "CVV": "801",            "Exp": "04/2025"        }    },    {        "CreditCard": {            "IssuingNetwork": "Discover",            "CardNumber": "6011999495570993",            "Name": "Walker Perez",            "Address": "White Street 125",            "Country": "Chile",            "CVV": "501",            "Exp": "05/2025"        }    },    {        "CreditCard": {            "IssuingNetwork": "Discover",            "CardNumber": "6011717325944505",            "Name": "Sophia White",            "Address": "Broad Street 136",            "Country": "New Zealand",            "CVV": "964",            "Exp": "12/2025"        }    },    {        "CreditCard": {            "IssuingNetwork": "Discover",            "CardNumber": "6011245097749753",            "Name": "Leonel Gonzalez",            "Address": "Olive Street 64",            "Country": "Singapore",            "CVV": "236",            "Exp": "01/2026"        }    },    {        "CreditCard": {            "IssuingNetwork": "Discover",            "CardNumber": "6011197847239397",            "Name": "Avery Turner",            "Address": "Franklin Avenue 4",            "Country": "Malaysia",            "CVV": "337",            "Exp": "06/2026"        }    },    {        "CreditCard": {            "IssuingNetwork": "Discover",            "CardNumber": "6011194247106771",            "Name": "Holly Lee",            "Address": "Franklin Avenue 33",            "Country": "Bulgaria",            "CVV": "163",            "Exp": "04/2019"        }    },    {        "CreditCard": {            "IssuingNetwork": "Discover",            "CardNumber": "6011322447094659",            "Name": "Deacon Lopez",            "Address": "Front Street North 57",            "Country": "Barbados",            "CVV": "906",            "Exp": "05/2023"        }    },    {        "CreditCard": {            "IssuingNetwork": "Discover",            "CardNumber": "6011160312325539",            "Name": "Jazlynn Baker",            "Address": "Olive Street 12",            "Country": "Maldives",            "CVV": "910",            "Exp": "09/2019"        }    },    {        "CreditCard": {            "IssuingNetwork": "Discover",            "CardNumber": "6011666968551251",            "Name": "Sydnee Perez",            "Address": "Cedar Avenue 11",            "Country": "Rwanda",            "CVV": "686",            "Exp": "08/2023"        }    },    {        "CreditCard": {            "IssuingNetwork": "Discover",            "CardNumber": "6011489361866980",            "Name": "Jackson Moore",            "Address": "Laurel Drive 30",            "Country": "Jamaica",            "CVV": "450",            "Exp": "06/2020"        }    },    {        "CreditCard": {            "IssuingNetwork": "Discover",            "CardNumber": "6011701457954292",            "Name": "Joy Taylor",            "Address": "John Street 124",            "Country": "Mauritania",            "CVV": "676",            "Exp": "04/2021"        }    },    {        "CreditCard": {            "IssuingNetwork": "Discover",            "CardNumber": "6011048415418451",            "Name": "Daniel Nelson",            "Address": "Rose Street 25",            "Country": "Colombia",            "CVV": "133",            "Exp": "12/2018"        }    },    {        "CreditCard": {            "IssuingNetwork": "Discover",            "CardNumber": "6011738028807294",            "Name": "Madison Gonzalez",            "Address": "Madison Avenue 86",            "Country": "Singapore",            "CVV": "170",            "Exp": "12/2018"        }    },    {        "CreditCard": {            "IssuingNetwork": "Discover",            "CardNumber": "6011660582879800",            "Name": "Landon Anderson",            "Address": "Franklin Court 50",            "Country": "Mali",            "CVV": "992",            "Exp": "09/2023"        }    },    {        "CreditCard": {            "IssuingNetwork": "Discover",            "CardNumber": "6011459373519844",            "Name": "Addison Phillips",            "Address": "Front Street North 107",            "Country": "Monaco",            "CVV": "655",            "Exp": "11/2020"        }    },    {        "CreditCard": {            "IssuingNetwork": "Discover",            "CardNumber": "6011105999211049",            "Name": "Anthony Miller",            "Address": "Country Club Road 95",            "Country": "Austria",            "CVV": "936",            "Exp": "06/2020"        }    },    {        "CreditCard": {            "IssuingNetwork": "Discover",            "CardNumber": "6011278282850920",            "Name": "Avery Green",            "Address": "Andover Court 76",            "Country": "Cyprus",            "CVV": "299",            "Exp": "12/2018"        }    },    {        "CreditCard": {            "IssuingNetwork": "Discover",            "CardNumber": "6011371437274839",            "Name": "Orion Davis",            "Address": "Pleasant Street 82",            "Country": "Madagascar",            "CVV": "239",            "Exp": "06/2022"        }    },    {        "CreditCard": {            "IssuingNetwork": "Discover",            "CardNumber": "6011127376933946",            "Name": "Orion Roberts",            "Address": "Country Club Road 139",            "Country": "Italy",            "CVV": "475",            "Exp": "12/2026"        }    },    {        "CreditCard": {            "IssuingNetwork": "Discover",            "CardNumber": "6011717967666622",            "Name": "Samantha Hernandez",            "Address": "Charles Street 56",            "Country": "Niger",            "CVV": "576",            "Exp": "10/2019"        }    },    {        "CreditCard": {            "IssuingNetwork": "Discover",            "CardNumber": "6011754297643989",            "Name": "David White",            "Address": "Clay Street 58",            "Country": "Singapore",            "CVV": "242",            "Exp": "08/2020"        }    },    {        "CreditCard": {            "IssuingNetwork": "Discover",            "CardNumber": "6011654024182576",            "Name": "Aiden Wilson",            "Address": "Olive Street 87",            "Country": "Philippines",            "CVV": "526",            "Exp": "01/2022"        }    },    {        "CreditCard": {            "IssuingNetwork": "Discover",            "CardNumber": "6011803105242938",            "Name": "Efrain Adams",            "Address": "Briarwood Drive 19",            "Country": "Sweden",            "CVV": "901",            "Exp": "08/2026"        }    },    {        "CreditCard": {            "IssuingNetwork": "Discover",            "CardNumber": "6011763632236995",            "Name": "Sebastian Nelson",            "Address": "Highland Drive 37",            "Country": "United Kingdom",            "CVV": "383",            "Exp": "07/2024"        }    },    {        "CreditCard": {            "IssuingNetwork": "Discover",            "CardNumber": "6011889066097486",            "Name": "Reuben Clark",            "Address": "Country Club Road 102",            "Country": "Croatia",            "CVV": "877",            "Exp": "04/2027"        }    },    {        "CreditCard": {            "IssuingNetwork": "Discover",            "CardNumber": "6011882291304546",            "Name": "Abraham Hill",            "Address": "Garfield Avenue 98",            "Country": "Colombia",            "CVV": "678",            "Exp": "08/2019"        }    },    {        "CreditCard": {            "IssuingNetwork": "Discover",            "CardNumber": "6011261104339702",            "Name": "Cesar Williams",            "Address": "Briarwood Drive 97",            "Country": "Singapore",            "CVV": "590",            "Exp": "02/2020"        }    },    {        "CreditCard": {            "IssuingNetwork": "Discover",            "CardNumber": "6011549300896339",            "Name": "Anthony Moore",            "Address": "Willow Avenue 76",            "Country": "Cambodia",            "CVV": "791",            "Exp": "12/2022"        }    },    {        "CreditCard": {            "IssuingNetwork": "Discover",            "CardNumber": "6011984080024234",            "Name": "Elizabeth Walker",            "Address": "Cedar Avenue 7",            "Country": "Thailand",            "CVV": "372",            "Exp": "02/2027"        }    },    {        "CreditCard": {            "IssuingNetwork": "Discover",            "CardNumber": "6011941937461431",            "Name": "Ryleigh Roberts",            "Address": "Cottage Street 94",            "Country": "Hong Kong",            "CVV": "551",            "Exp": "09/2023"        }    },    {        "CreditCard": {            "IssuingNetwork": "Discover",            "CardNumber": "6011217855484220",            "Name": "Jolie Evans",            "Address": "Hanover Court 124",            "Country": "Switzerland",            "CVV": "836",            "Exp": "11/2019"        }    },    {        "CreditCard": {            "IssuingNetwork": "Discover",            "CardNumber": "6011377766142042",            "Name": "Gabriel Hall",            "Address": "Forest Street 147",            "Country": "Italy",            "CVV": "230",            "Exp": "09/2026"        }    },    {        "CreditCard": {            "IssuingNetwork": "Discover",            "CardNumber": "6011358703490322",            "Name": "Brooklyn White",            "Address": "Cedar Avenue 141",            "Country": "Philippines",            "CVV": "753",            "Exp": "05/2027"        }    },    {        "CreditCard": {            "IssuingNetwork": "Discover",            "CardNumber": "6011346993299867",            "Name": "Troy Johnson",            "Address": "Windsor Drive 11",            "Country": "Sweden",            "CVV": "165",            "Exp": "06/2022"        }    },    {        "CreditCard": {            "IssuingNetwork": "Discover",            "CardNumber": "6011872167280789",            "Name": "David Moore",            "Address": "Highland Drive 112",            "Country": "Hungary",            "CVV": "474",            "Exp": "06/2026"        }    },    {        "CreditCard": {            "IssuingNetwork": "Discover",            "CardNumber": "6011351742694939",            "Name": "Tyrese Rodriguez",            "Address": "Devon Court 40",            "Country": "Liberia",            "CVV": "695",            "Exp": "01/2026"        }    },    {        "CreditCard": {            "IssuingNetwork": "Discover",            "CardNumber": "6011769396591434",            "Name": "Rogelio Turner",            "Address": "Heather Lane 47",            "Country": "Italy",            "CVV": "351",            "Exp": "07/2027"        }    },    {        "CreditCard": {            "IssuingNetwork": "Discover",            "CardNumber": "6011167503691041",            "Name": "Ashley Thompson",            "Address": "Fairway Drive 56",            "Country": "Afghanistan",            "CVV": "341",            "Exp": "12/2018"        }    },    {        "CreditCard": {            "IssuingNetwork": "Discover",            "CardNumber": "6011111928819365",            "Name": "Vivian Jones",            "Address": "White Street 103",            "Country": "Singapore",            "CVV": "730",            "Exp": "08/2020"        }    },    {        "CreditCard": {            "IssuingNetwork": "Discover",            "CardNumber": "6011107060034235",            "Name": "Elizabeth Gonzalez",            "Address": "Route 30 23",            "Country": "United Kingdom",            "CVV": "612",            "Exp": "04/2023"        }    },    {        "CreditCard": {            "IssuingNetwork": "Discover",            "CardNumber": "6011298922433440",            "Name": "Deacon Moore",            "Address": "Ann Street 108",            "Country": "Romania",            "CVV": "788",            "Exp": "04/2024"        }    },    {        "CreditCard": {            "IssuingNetwork": "Discover",            "CardNumber": "6011831404588727",            "Name": "Sophia Anderson",            "Address": "John Street 137",            "Country": "Luxembourg",            "CVV": "219",            "Exp": "06/2022"        }    },    {        "CreditCard": {            "IssuingNetwork": "Discover",            "CardNumber": "6011172361690580",            "Name": "Jayden Davis",            "Address": "Briarwood Drive 146",            "Country": "Mauritania",            "CVV": "733",            "Exp": "01/2020"        }    },    {        "CreditCard": {            "IssuingNetwork": "Discover",            "CardNumber": "6011973986596437",            "Name": "Olivia Baker",            "Address": "Essex Court 89",            "Country": "Italy",            "CVV": "954",            "Exp": "10/2025"        }    },    {        "CreditCard": {            "IssuingNetwork": "Discover",            "CardNumber": "6011743237712426",            "Name": "Elizabeth Baker",            "Address": "Monroe Street 120",            "Country": "Canada",            "CVV": "863",            "Exp": "12/2018"        }    },    {        "CreditCard": {            "IssuingNetwork": "Discover",            "CardNumber": "6011486814709585",            "Name": "Caden Harris",            "Address": "Maiden Lane 131",            "Country": "Sri Lanka",            "CVV": "480",            "Exp": "08/2022"        }    },    {        "CreditCard": {            "IssuingNetwork": "Discover",            "CardNumber": "6011262033636291",            "Name": "Gabriel Thompson",            "Address": "Court Street 40",            "Country": "Gambia",            "CVV": "574",            "Exp": "03/2027"        }    },    {        "CreditCard": {            "IssuingNetwork": "Discover",            "CardNumber": "6011013218468103",            "Name": "Brenton Carter",            "Address": "Highland Drive 79",            "Country": "Netherlands",            "CVV": "629",            "Exp": "02/2027"        }    },    {        "CreditCard": {            "IssuingNetwork": "Discover",            "CardNumber": "6011460586247421",            "Name": "Diamond Lewis",            "Address": "River Street 66",            "Country": "Malaysia",            "CVV": "238",            "Exp": "02/2022"        }    },    {        "CreditCard": {            "IssuingNetwork": "Discover",            "CardNumber": "6011065637340008",            "Name": "Anthony Walker",            "Address": "Court Street 143",            "Country": "Tunisia",            "CVV": "928",            "Exp": "07/2026"        }    },    {        "CreditCard": {            "IssuingNetwork": "Discover",            "CardNumber": "6011882545945938",            "Name": "Mia Gonzalez",            "Address": "Charles Street 74",            "Country": "Sudan",            "CVV": "682",            "Exp": "06/2020"        }    },    {        "CreditCard": {            "IssuingNetwork": "Discover",            "CardNumber": "6011649160753040",            "Name": "Rogelio Thompson",            "Address": "Willow Avenue 34",            "Country": "Italy",            "CVV": "596",            "Exp": "09/2020"        }    },    {        "CreditCard": {            "IssuingNetwork": "Discover",            "CardNumber": "6011725334546567",            "Name": "Ruby Thompson",            "Address": "Madison Avenue 131",            "Country": "Fiji",            "CVV": "508",            "Exp": "12/2024"        }    },    {        "CreditCard": {            "IssuingNetwork": "Discover",            "CardNumber": "6011546774546556",            "Name": "Cecelia Allen",            "Address": "Garfield Avenue 19",            "Country": "Comoros",            "CVV": "825",            "Exp": "01/2025"        }    },    {        "CreditCard": {            "IssuingNetwork": "Discover",            "CardNumber": "6011470556548997",            "Name": "David Nelson",            "Address": "Windsor Drive 45",            "Country": "Luxembourg",            "CVV": "352",            "Exp": "04/2023"        }    },    {        "CreditCard": {            "IssuingNetwork": "Discover",            "CardNumber": "6011967244340968",            "Name": "Ryan Johnson",            "Address": "Olive Street 4",            "Country": "Thailand",            "CVV": "581",            "Exp": "03/2022"        }    },    {        "CreditCard": {            "IssuingNetwork": "Discover",            "CardNumber": "6011796572845870",            "Name": "Xzavier Gonzalez",            "Address": "Essex Court 116",            "Country": "Jordan",            "CVV": "653",            "Exp": "09/2025"        }    },    {        "CreditCard": {            "IssuingNetwork": "Discover",            "CardNumber": "6011132064869410",            "Name": "Cesar Lewis",            "Address": "Route 1 18",            "Country": "Malaysia",            "CVV": "154",            "Exp": "12/2019"        }    },    {        "CreditCard": {            "IssuingNetwork": "Discover",            "CardNumber": "6011895631117261",            "Name": "William Hernandez",            "Address": "Route 30 23",            "Country": "Netherlands",            "CVV": "586",            "Exp": "06/2025"        }    },    {        "CreditCard": {            "IssuingNetwork": "Discover",            "CardNumber": "6011470729586650",            "Name": "Glenn Mitchell",            "Address": "Highland Drive 29",            "Country": "Kazakhstan",            "CVV": "281",            "Exp": "01/2024"        }    },    {        "CreditCard": {            "IssuingNetwork": "Discover",            "CardNumber": "6011302792575064",            "Name": "Elijah Jones",            "Address": "Summit Avenue 70",            "Country": "France",            "CVV": "355",            "Exp": "09/2026"        }    },    {        "CreditCard": {            "IssuingNetwork": "Discover",            "CardNumber": "6011167378571450",            "Name": "Julia Gonzalez",            "Address": "Briarwood Drive 144",            "Country": "Vanuatu",            "CVV": "140",            "Exp": "10/2024"        }    },    {        "CreditCard": {            "IssuingNetwork": "Discover",            "CardNumber": "6011201398422269",            "Name": "Jazlynn Rodriguez",            "Address": "Hanover Court 44",            "Country": "Jordan",            "CVV": "500",            "Exp": "03/2020"        }    },    {        "CreditCard": {            "IssuingNetwork": "Discover",            "CardNumber": "6011377208630562",            "Name": "Julia Taylor",            "Address": "King Street 109",            "Country": "Gambia",            "CVV": "946",            "Exp": "10/2023"        }    },    {        "CreditCard": {            "IssuingNetwork": "Discover",            "CardNumber": "6011866940605783",            "Name": "Anthony Garcia",            "Address": "Laurel Drive 121",            "Country": "United Kingdom",            "CVV": "328",            "Exp": "11/2020"        }    },    {        "CreditCard": {            "IssuingNetwork": "Discover",            "CardNumber": "6011991101242000",            "Name": "Leonel Nelson",            "Address": "Laurel Lane 55",            "Country": "Bolivia",            "CVV": "778",            "Exp": "08/2024"        }    },    {        "CreditCard": {            "IssuingNetwork": "Discover",            "CardNumber": "6011862824739483",            "Name": "Rogelio Baker",            "Address": "Hanover Court 97",            "Country": "Chad",            "CVV": "914",            "Exp": "03/2024"        }    },    {        "CreditCard": {            "IssuingNetwork": "Discover",            "CardNumber": "6011391031810473",            "Name": "Rihanna Baker",            "Address": "Franklin Avenue 56",            "Country": "Morocco",            "CVV": "124",            "Exp": "06/2020"        }    },    {        "CreditCard": {            "IssuingNetwork": "Discover",            "CardNumber": "6011557215699011",            "Name": "Ethen Gonzalez",            "Address": "Crescent Street 67",            "Country": "Netherlands",            "CVV": "290",            "Exp": "10/2022"        }    },    {        "CreditCard": {            "IssuingNetwork": "Discover",            "CardNumber": "6011660192584675",            "Name": "Elvis Moore",            "Address": "Maiden Lane 80",            "Country": "Sweden",            "CVV": "997",            "Exp": "11/2023"        }    },    {        "CreditCard": {            "IssuingNetwork": "Discover",            "CardNumber": "6011207816499177",            "Name": "Reagan Mitchell",            "Address": "Devon Court 34",            "Country": "Malaysia",            "CVV": "137",            "Exp": "08/2025"        }    },    {        "CreditCard": {            "IssuingNetwork": "Discover",            "CardNumber": "6011482952250243",            "Name": "Yamilet Smith",            "Address": "Hanover Court 26",            "Country": "Mauritania",            "CVV": "850",            "Exp": "07/2020"        }    },    {        "CreditCard": {            "IssuingNetwork": "Discover",            "CardNumber": "6011425430423189",            "Name": "Selina Wright",            "Address": "King Street 110",            "Country": "Belarus",            "CVV": "401",            "Exp": "03/2023"        }    },    {        "CreditCard": {            "IssuingNetwork": "Discover",            "CardNumber": "6011698706475535",            "Name": "Anna Baker",            "Address": "Ann Street 67",            "Country": "Solomon Islands",            "CVV": "920",            "Exp": "09/2025"        }    },    {        "CreditCard": {            "IssuingNetwork": "Discover",            "CardNumber": "6011514440186785",            "Name": "Glenn Williams",            "Address": "Windsor Drive 119",            "Country": "Benin",            "CVV": "702",            "Exp": "03/2025"        }    },    {        "CreditCard": {            "IssuingNetwork": "Discover",            "CardNumber": "6011299780493443",            "Name": "Van Walker",            "Address": "Court Street 57",            "Country": "Latvia",            "CVV": "271",            "Exp": "12/2018"        }    },    {        "CreditCard": {            "IssuingNetwork": "Discover",            "CardNumber": "6011477532536061",            "Name": "Emma Wright",            "Address": "Hanover Court 31",            "Country": "Uruguay",            "CVV": "542",            "Exp": "12/2019"        }    },    {        "CreditCard": {            "IssuingNetwork": "Discover",            "CardNumber": "6011183592217796",            "Name": "Etha Hill",            "Address": "Main Street 45",            "Country": "New Zealand",            "CVV": "336",            "Exp": "06/2027"        }    },    {        "CreditCard": {            "IssuingNetwork": "Discover",            "CardNumber": "6011418255190256",            "Name": "Aydan Moore",            "Address": "Warren Avenue 39",            "Country": "Samoa",            "CVV": "670",            "Exp": "07/2020"        }    },    {        "CreditCard": {            "IssuingNetwork": "Discover",            "CardNumber": "6011864330244800",            "Name": "Sebastian Parker",            "Address": "Hanover Court 101",            "Country": "Hong Kong",            "CVV": "998",            "Exp": "12/2018"        }    },    {        "CreditCard": {            "IssuingNetwork": "Discover",            "CardNumber": "6011589193973910",            "Name": "Katherine Green",            "Address": "Court Street 120",            "Country": "Paraguay",            "CVV": "304",            "Exp": "04/2020"        }    },    {        "CreditCard": {            "IssuingNetwork": "Discover",            "CardNumber": "6011659167922936",            "Name": "Caden Hall",            "Address": "Briarwood Drive 54",            "Country": "Uruguay",            "CVV": "350",            "Exp": "05/2025"        }    },    {        "CreditCard": {            "IssuingNetwork": "Discover",            "CardNumber": "6011455288050230",            "Name": "Michael Lopez",            "Address": "John Street 132",            "Country": "Belgium",            "CVV": "762",            "Exp": "03/2023"        }    },    {        "CreditCard": {            "IssuingNetwork": "Discover",            "CardNumber": "6011393581361352",            "Name": "Jayden Campbell",            "Address": "Windsor Drive 31",            "Country": "Croatia",            "CVV": "709",            "Exp": "10/2025"        }    },    {        "CreditCard": {            "IssuingNetwork": "Discover",            "CardNumber": "6011701183246807",            "Name": "Harry Jones",            "Address": "Court Street 35",            "Country": "Nigeria",            "CVV": "711",            "Exp": "07/2020"        }    },    {        "CreditCard": {            "IssuingNetwork": "Discover",            "CardNumber": "6011461522564564",            "Name": "Ruby Hernandez",            "Address": "Ann Street 57",            "Country": "Seychelles",            "CVV": "193",            "Exp": "01/2026"        }    },    {        "CreditCard": {            "IssuingNetwork": "Discover",            "CardNumber": "6011630141270700",            "Name": "Emmanuel Evans",            "Address": "Pleasant Street 13",            "Country": "New Caledonia",            "CVV": "691",            "Exp": "01/2023"        }    },    {        "CreditCard": {            "IssuingNetwork": "Discover",            "CardNumber": "6011890473958070",            "Name": "Riley King",            "Address": "Cedar Avenue 29",            "Country": "Lesotho",            "CVV": "731",            "Exp": "07/2027"        }    },    {        "CreditCard": {            "IssuingNetwork": "Discover",            "CardNumber": "6011730276317415",            "Name": "Malcolm Jones",            "Address": "Linden Avenue 84",            "Country": "Comoros",            "CVV": "600",            "Exp": "01/2023"        }    },    {        "CreditCard": {            "IssuingNetwork": "Discover",            "CardNumber": "6011346745013640",            "Name": "Aiden Hill",            "Address": "Windsor Drive 111",            "Country": "Singapore",            "CVV": "416",            "Exp": "12/2018"        }    },    {        "CreditCard": {            "IssuingNetwork": "Discover",            "CardNumber": "6011366942555326",            "Name": "Marisol Allen",            "Address": "Crescent Street 17",            "Country": "Romania",            "CVV": "259",            "Exp": "11/2026"        }    },    {        "CreditCard": {            "IssuingNetwork": "Discover",            "CardNumber": "6011563048521471",            "Name": "Saige Wilson",            "Address": "Broad Street 35",            "Country": "Sierra Leone",            "CVV": "786",            "Exp": "03/2019"        }    },    {        "CreditCard": {            "IssuingNetwork": "Discover",            "CardNumber": "6011991538573407",            "Name": "Samantha Garcia",            "Address": "Front Street North 147",            "Country": "Marshall Islands",            "CVV": "606",            "Exp": "04/2024"        }    },    {        "CreditCard": {            "IssuingNetwork": "Discover",            "CardNumber": "6011210664520698",            "Name": "Malcolm Miller",            "Address": "King Street 47",            "Country": "Honduras",            "CVV": "434",            "Exp": "05/2019"        }    },    {        "CreditCard": {            "IssuingNetwork": "Discover",            "CardNumber": "6011004599443252",            "Name": "Eliana Harris",            "Address": "River Street 143",            "Country": "Sierra Leone",            "CVV": "767",            "Exp": "05/2027"        }    },    {        "CreditCard": {            "IssuingNetwork": "Discover",            "CardNumber": "6011965166827749",            "Name": "Ryleigh Roberts",            "Address": "Route 1 13",            "Country": "Greenland",            "CVV": "502",            "Exp": "05/2020"        }    },    {        "CreditCard": {            "IssuingNetwork": "Discover",            "CardNumber": "6011144261199475",            "Name": "Ashley Davis",            "Address": "Highland Drive 5",            "Country": "United States",            "CVV": "790",            "Exp": "09/2022"        }    },    {        "CreditCard": {            "IssuingNetwork": "Discover",            "CardNumber": "6011947168771034",            "Name": "Brooklyn Harris",            "Address": "John Street 44",            "Country": "Ethiopia",            "CVV": "854",            "Exp": "08/2021"        }    },    {        "CreditCard": {            "IssuingNetwork": "Discover",            "CardNumber": "6011458415531148",            "Name": "Mohammad Carter",            "Address": "Fairway Drive 112",            "Country": "Netherlands",            "CVV": "881",            "Exp": "02/2020"        }    },    {        "CreditCard": {            "IssuingNetwork": "Discover",            "CardNumber": "6011511218141158",            "Name": "Van Anderson",            "Address": "Fairway Drive 3",            "Country": "France",            "CVV": "509",            "Exp": "12/2022"        }    },    {        "CreditCard": {            "IssuingNetwork": "Discover",            "CardNumber": "6011354426009515",            "Name": "Dexter Johnson",            "Address": "Jefferson Avenue 56",            "Country": "Australia",            "CVV": "473",            "Exp": "04/2025"        }    },    {        "CreditCard": {            "IssuingNetwork": "Discover",            "CardNumber": "6011428578584994",            "Name": "Ethen Smith",            "Address": "Windsor Drive 133",            "Country": "India",            "CVV": "623",            "Exp": "11/2026"        }    },    {        "CreditCard": {            "IssuingNetwork": "Discover",            "CardNumber": "6011674921669228",            "Name": "Cierra Hall",            "Address": "Franklin Court 88",            "Country": "Malaysia",            "CVV": "342",            "Exp": "04/2021"        }    },    {        "CreditCard": {            "IssuingNetwork": "Discover",            "CardNumber": "6011783420107067",            "Name": "David King",            "Address": "Court Street 57",            "Country": "Fiji",            "CVV": "979",            "Exp": "05/2024"        }    }]